SBI/__init__.py
SBI/_version.py
SBI/beans/Executable.py
SBI/beans/IndexedNum.py
SBI/beans/JSONer.py
SBI/beans/Path.py
SBI/beans/StorableObject.py
SBI/beans/__init__.py
SBI/beans/butler.py
SBI/beans/file.py
SBI/beans/singleton.py
SBI/core/__init__.py
SBI/core/core_init.py
SBI/data/Alphabet.py
SBI/data/AminoAcids.py
SBI/data/AtomVariants.py
SBI/data/Element.py
SBI/data/Properties.py
SBI/data/SetDict.py
SBI/data/__init__.py
SBI/data/alphabet.csv.gz
SBI/databases/CATHlink.py
SBI/databases/DrugBanklink.py
SBI/databases/Enzymelink.py
SBI/databases/GOlink.py
SBI/databases/PDBTMlink.py
SBI/databases/PDBeChemConnect.py
SBI/databases/PDBeChemlink.py
SBI/databases/PDBlink.py
SBI/databases/SCOPlink.py
SBI/databases/TaxIDlink.py
SBI/databases/__Uniprotlink.py
SBI/databases/__init__.py
SBI/databases/dblink.py
SBI/databases/uniprot/__init__.py
SBI/databases/uniprot/connect.py
SBI/databases/uniprot/uniprot.py
SBI/external/ExeBase.py
SBI/external/ExternalExe.py
SBI/external/__init__.py
SBI/external/CDhit/CDhit.py
SBI/external/CDhit/CDhitExe.py
SBI/external/CDhit/CDhitHomolog.py
SBI/external/CDhit/CDhitList.py
SBI/external/CDhit/__init__.py
SBI/external/DSSP/DSSP.py
SBI/external/DSSP/DSSPExe.py
SBI/external/DSSP/__init__.py
SBI/external/blast/BlastExe.py
SBI/external/blast/BlastHit.py
SBI/external/blast/BlastResult.py
SBI/external/blast/__init__.py
SBI/external/hmmer/HmmExe.py
SBI/external/hmmer/HmmHit.py
SBI/external/hmmer/HmmResult.py
SBI/external/hmmer/__init__.py
SBI/math/__init__.py
SBI/math/stats.py
SBI/sequence/Fasta.py
SBI/sequence/Sequence.py
SBI/sequence/__init__.py
SBI/sequence/alignment/Needleman_Wunsch.py
SBI/sequence/alignment/SeqAli.py
SBI/sequence/alignment/SimilarityMatrix.py
SBI/sequence/alignment/__init__.py
SBI/structure/Frame3D.py
SBI/structure/PDBContainer.py
SBI/structure/_PDB.py
SBI/structure/__init__.py
SBI/structure/parse_pdb.py
SBI/structure/_header/BioMolecule.py
SBI/structure/_header/DBreference.py
SBI/structure/_header/Experiment.py
StrBioInfo-0.9a0.dev1.dist-info/LICENSE
StrBioInfo-0.9a0.dev1.dist-info/METADATA
StrBioInfo-0.9a0.dev1.dist-info/WHEEL
StrBioInfo-0.9a0.dev1.dist-info/entry_points.txt
StrBioInfo-0.9a0.dev1.dist-info/top_level.txt
StrBioInfo-0.9a0.dev1.dist-info/RECORD
